<?xml version="1.0" encoding="utf-8"?>
<!DOCTYPE hibernate-mapping PUBLIC "-//Hibernate/Hibernate Mapping DTD 3.0//EN"
"http://hibernate.sourceforge.net/hibernate-mapping-3.0.dtd">
<!-- 
    Mapping file autogenerated by MyEclipse Persistence Tools
-->
<hibernate-mapping>
    <class name="com.njmd.pojo.FrameTree" table="FRAME_TREE">
        <comment>部门级别规划表</comment>
        <id name="treeId" type="java.lang.Long">
            <column name="TREE_ID" precision="10" scale="0" />
            <generator class="sequence" >
            	<param name="sequence">SEQ_TREE_ID</param>
            </generator>
        </id>
        <property name="treeName" type="java.lang.String">
            <column name="TREE_NAME" length="50">
                <comment>部门名称</comment>
            </column>
        </property>
        <property name="treeDesc" type="java.lang.String">
            <column name="TREE_DESC" length="200">
                <comment>部门描述</comment>
            </column>
        </property>
        <property name="treeState" type="java.lang.String">
            <column name="TREE_STATE" length="1">
                <comment>状态：A-有效；U-无效</comment>
            </column>
        </property>
        <property name="createUser" type="java.lang.Long">
            <column name="CREATE_USER" precision="10" scale="0">
                <comment>创建人userid</comment>
            </column>
        </property>
        <property name="createTime" type="java.lang.String">
            <column name="CREATE_TIME" length="14">
                <comment>创建时间</comment>
            </column>
        </property>
        <property name="parentTreeId" type="java.lang.Long">
            <column name="PARENT_TREE_ID" precision="10" scale="0">
                <comment>所属部门 （一级部门时为0）</comment>
            </column>
        </property>
        <property name="orderBy" type="java.lang.Long">
            <column name="ORDER_BY" precision="3" scale="0">
                <comment>排序</comment>
            </column>
        </property>
        <property name="path" type="java.lang.String">
            <column name="PATH" length="100">
                <comment>部门路径</comment>
            </column>
        </property>
    </class>
</hibernate-mapping>
